lab2_hw/lab2.v
// pipelined fast multiplier
module mult_fast(
	output reg[7:0] P,  // product
	input[3:0] A, B,    // multiplicand and multiplier
	input clk		    // clock (posedge)
	);
	// stage 0 (input)
	reg[3:0] a_s0, b_s0;
	always @(posedge clk) begin
		a_s0 <= A;
		b_s0 <= B;
	end
	// stage 1
	wire[3:0] pp0 = a_s0 & {4{b_s0[0]}}; // ignore the delays of AND gates
	wire[4:1] pp1 = a_s0 & {4{b_s0[1]}}; // ignore the delays of AND gates
	wire[5:2] pp2 = a_s0 & {4{b_s0[2]}}; // ignore the delays of AND gates
	wire[6:3] pp3 = a_s0 & {4{b_s0[3]}}; // ignore the delays of AND gates
	reg[5:1] sum1;
	always @(pp0, pp1)
		sum1[5:1] <= #7 pp0[3:1] + pp1[4:1]; // delay of the 4-bit adder
	reg[7:3] sum3;
	always @(pp2, pp3)
		sum3[7:3] <= #7 pp2[5:3] + pp3[6:3]; // delay of the 4-bit adder
	reg[5:0] sum1_s1;
	reg[7:2] sum3_s1;
	always @(posedge clk) begin
		sum1_s1 <= {sum1, pp0[0]};
		sum3_s1 <= {sum3, pp2[2]};
	end
	// stage 2 (outout)
	reg[7:2] sum2;
	always @(sum1_s1, sum3_s1)
		sum2[7:2] <= #8 sum1_s1[5:2] + sum3_s1[7:2]; // delay of the 6-bit adder
	always @(posedge clk) begin
		P <= {sum2, sum1_s1[1:0]};
	end
endmodule

// test bench
module mult_tb();
	// dump
	initial begin
		$dumpfile("lab2.vcd");
		$dumpvars(0, mult_tb);
	end
	// clock cycle = 10 ticks
	reg clock = 1;
	always
		#4 clock <= ~clock;
	// multiplier
	reg[3:0] A, B;
	wire[7:0] P;
	reg[7:0] P_ref;
	mult_fast mult(P, A, B, clock);
	always @(posedge clock)
		P_ref <= #10 A*B;
	// loop through all possible inputs
	integer i;
	initial begin
		#9;
		for(i=0; i<256; i=i+1) begin
			{A, B} <= i;
			#21;
		end
		#9 $finish;
	end
	// check if the products are correct
	reg[3:0] A_old, B_old;
	always @(posedge clock) begin
		#1
		if(P_ref!=P && i>=2) begin
			A_old = (i-2)/16;
			B_old = (i-2)%16;
			$display("Product is wrong when A=%b, B=%b.", A_old, B_old);
			$display("P_ref: %b.", P_ref);
			$display("P    : %b.", P);
			#9 $finish;
		end
	end
endmodule

lab2_hw/lab2.vcd
$date
	Mon Jun 03 13:28:52 2019
$end
$version
	Icarus Verilog
$end
$timescale
	1s
$end
$scope module mult_tb $end
$var wire 8 ! P [7:0] $end
$var reg 4 " A [3:0] $end
$var reg 4 # A_old [3:0] $end
$var reg 4 $ B [3:0] $end
$var reg 4 % B_old [3:0] $end
$var reg 8 & P_ref [7:0] $end
$var reg 1 ' clock $end
$var integer 32 ( i [31:0] $end
$scope module mult $end
$var wire 4 ) A [3:0] $end
$var wire 4 * B [3:0] $end
$var wire 1 + clk $end
$var wire 4 , pp0 [3:0] $end
$var wire 4 - pp1 [4:1] $end
$var wire 4 . pp2 [5:2] $end
$var wire 4 / pp3 [6:3] $end
$var reg 8 0 P [7:0] $end
$var reg 4 1 a_s0 [3:0] $end
$var reg 4 2 b_s0 [3:0] $end
$var reg 5 3 sum1 [5:1] $end
$var reg 6 4 sum1_s1 [5:0] $end
$var reg 6 5 sum2 [7:2] $end
$var reg 5 6 sum3 [7:3] $end
$var reg 6 7 sum3_s1 [7:2] $end
$upscope $end
$upscope $end
$enddefinitions $end
#0
$dumpvars
bx 7
bx 6
bx 5
bx 4
bx 3
bx 2
bx 1
bx 0
bx /
bx .
bx -
bx ,
1+
bx *
bx )
bx (
1'
bx &
bx %
bx $
bx #
bx "
bx !
$end
#4
0'
0+
#8
1'
1+
#9
b0 "
b0 )
b0 $
b0 *
b0 (
#12
0'
0+
#16
b0 /
b0 .
b0 -
b0 ,
b0 2
b0 1
1'
1+
#20
0'
0+
#23
b0 6
b0 3
#24
b0 7
b0 4
1'
1+
#26
b0 &
#28
0'
0+
#30
b1 $
b1 *
b1 (
#32
b1 2
b0 0
b0 !
1'
1+
b0 5
#36
0'
0+
#40
1'
1+
#44
0'
0+
#48
1'
1+
#51
b10 $
b10 *
b10 (
#52
0'
0+
#56
b10 2
1'
1+
#60
0'
0+
#64
1'
1+
#68
0'
0+
#72
b11 2
1'
1+
b11 $
b11 *
b11 (
#76
0'
0+
#80
1'
1+
#84
0'
0+
#88
1'
1+
#92
0'
0+
#93
b100 $
b100 *
b100 (
#96
b100 2
1'
1+
#100
0'
0+
#104
1'
1+
#108
0'
0+
#112
1'
1+
#114
b101 $
b101 *
b101 (
#116
0'
0+
#120
b101 2
1'
1+
#124
0'
0+
#128
1'
1+
#132
0'
0+
#135
b110 $
b110 *
b110 (
#136
b110 2
1'
1+
#140
0'
0+
#144
1'
1+
#148
0'
0+
#152
1'
1+
#156
0'
0+
b111 $
b111 *
b111 (
#160
b111 2
1'
1+
#164
0'
0+
#168
1'
1+
#172
0'
0+
#176
1'
1+
#177
b1000 $
b1000 *
b1000 (
#180
0'
0+
#184
b1000 2
1'
1+
#188
0'
0+
#192
1'
1+
#196
0'
0+
#198
b1001 $
b1001 *
b1001 (
#200
b1001 2
1'
1+
#204
0'
0+
#208
1'
1+
#212
0'
0+
#216
1'
1+
#219
b1010 $
b1010 *
b1010 (
#220
0'
0+
#224
b1010 2
1'
1+
#228
0'
0+
#232
1'
1+
#236
0'
0+
#240
b1011 2
1'
1+
b1011 $
b1011 *
b1011 (
#244
0'
0+
#248
1'
1+
#252
0'
0+
#256
1'
1+
#260
0'
0+
#261
b1100 $
b1100 *
b1100 (
#264
b1100 2
1'
1+
#268
0'
0+
#272
1'
1+
#276
0'
0+
#280
1'
1+
#282
b1101 $
b1101 *
b1101 (
#284
0'
0+
#288
b1101 2
1'
1+
#292
0'
0+
#296
1'
1+
#300
0'
0+
#303
b1110 $
b1110 *
b1110 (
#304
b1110 2
1'
1+
#308
0'
0+
#312
1'
1+
#316
0'
0+
#320
1'
1+
#324
0'
0+
b1111 $
b1111 *
b1111 (
#328
b1111 2
1'
1+
#332
0'
0+
#336
1'
1+
#340
0'
0+
#344
1'
1+
#345
b1 "
b1 )
b0 $
b0 *
b10000 (
#348
0'
0+
#352
b0 /
b0 .
b0 -
b0 ,
b0 2
b1 1
1'
1+
#356
0'
0+
#359
b0 6
b0 3
#360
1'
1+
#364
0'
0+
#366
b1 $
b1 *
b10001 (
#368
b1 ,
b1 2
1'
1+
#372
0'
0+
#376
b1 4
1'
1+
#378
b1 &
#380
0'
0+
#384
b1 0
b1 !
1'
1+
#387
b10 $
b10 *
b10010 (
#388
0'
0+
#392
b0 ,
b1 -
b10 2
1'
1+
#396
0'
0+
#399
b1 3
#400
b10 4
1'
1+
#402
b10 &
#404
0'
0+
#408
b1 ,
b10 0
b10 !
b11 2
1'
1+
b11 $
b11 *
b10011 (
#412
0'
0+
#416
b11 4
1'
1+
#418
b11 &
#420
0'
0+
#424
b11 0
b11 !
1'
1+
#428
0'
0+
#429
b100 $
b100 *
b10100 (
#432
b0 ,
b0 -
b1 .
b100 2
1'
1+
#436
0'
0+
#439
b0 3
#440
b1 7
b0 4
1'
1+
#442
b100 &
#444
0'
0+
#448
b100 0
b100 !
1'
1+
b1 5
#450
b101 $
b101 *
b10101 (
#452
0'
0+
#456
b1 ,
b101 2
1'
1+
#460
0'
0+
#464
b1 4
1'
1+
#466
b101 &
#468
0'
0+
#471
b110 $
b110 *
b10110 (
#472
b0 ,
b1 -
b101 0
b101 !
b110 2
1'
1+
#476
0'
0+
#479
b1 3
#480
b10 4
1'
1+
#482
b110 &
#484
0'
0+
#488
b110 0
b110 !
1'
1+
#492
0'
0+
b111 $
b111 *
b10111 (
#496
b1 ,
b111 2
1'
1+
#500
0'
0+
#504
b11 4
1'
1+
#506
b111 &
#508
0'
0+
#512
b111 0
b111 !
1'
1+
#513
b1000 $
b1000 *
b11000 (
#516
0'
0+
#520
b0 ,
b0 -
b0 .
b1 /
b1000 2
1'
1+
#524
0'
0+
#527
b0 3
b1 6
#528
b10 7
b0 4
1'
1+
#530
b1000 &
#532
0'
0+
#534
b1001 $
b1001 *
b11001 (
#536
b1 ,
b1000 0
b1000 !
b1001 2
1'
1+
b10 5
#540
0'
0+
#544
b1 4
1'
1+
#546
b1001 &
#548
0'
0+
#552
b1001 0
b1001 !
1'
1+
#555
b1010 $
b1010 *
b11010 (
#556
0'
0+
#560
b0 ,
b1 -
b1010 2
1'
1+
#564
0'
0+
#567
b1 3
#568
b10 4
1'
1+
#570
b1010 &
#572
0'
0+
#576
b1 ,
b1011 2
b1010 0
b1010 !
1'
1+
b1011 $
b1011 *
b11011 (
#580
0'
0+
#584
b11 4
1'
1+
#586
b1011 &
#588
0'
0+
#592
b1011 0
b1011 !
1'
1+
#596
0'
0+
#597
b1100 $
b1100 *
b11100 (
#600
b0 ,
b0 -
b1 .
b1100 2
1'
1+
#604
0'
0+
#607
b0 3
#608
b11 7
b0 4
1'
1+
#610
b1100 &
#612
0'
0+
#616
b1100 0
b1100 !
1'
1+
b11 5
#618
b1101 $
b1101 *
b11101 (
#620
0'
0+
#624
b1 ,
b1101 2
1'
1+
#628
0'
0+
#632
b1 4
1'
1+
#634
b1101 &
#636
0'
0+
#639
b1110 $
b1110 *
b11110 (
#640
b0 ,
b1 -
b1110 2
b1101 0
b1101 !
1'
1+
#644
0'
0+
#647
b1 3
#648
b10 4
1'
1+
#650
b1110 &
#652
0'
0+
#656
b1110 0
b1110 !
1'
1+
#660
0'
0+
b1111 $
b1111 *
b11111 (
#664
b1 ,
b1111 2
1'
1+
#668
0'
0+
#672
b11 4
1'
1+
#674
b1111 &
#676
0'
0+
#680
b1111 0
b1111 !
1'
1+
#681
b10 "
b10 )
b0 $
b0 *
b100000 (
#684
0'
0+
#688
b0 /
b0 .
b0 -
b0 ,
b0 2
b10 1
1'
1+
#692
0'
0+
#695
b0 6
b0 3
#696
b0 7
b0 4
1'
1+
#698
b0 &
#700
0'
0+
#702
b1 $
b1 *
b100001 (
#704
b10 ,
b1 2
b0 0
b0 !
1'
1+
b0 5
#708
0'
0+
#711
b1 3
#712
b10 4
1'
1+
#714
b10 &
#716
0'
0+
#720
b10 0
b10 !
1'
1+
#723
b10 $
b10 *
b100010 (
#724
0'
0+
#728
b0 ,
b10 -
b10 2
1'
1+
#732
0'
0+
#735
b10 3
#736
b100 4
1'
1+
#738
b100 &
#740
0'
0+
#744
b10 ,
b100 0
b100 !
b11 2
1'
1+
b11 $
b11 *
b1 5
b100011 (
#748
0'
0+
#751
b11 3
#752
b110 4
1'
1+
#754
b110 &
#756
0'
0+
#760
b110 0
b110 !
1'
1+
#764
0'
0+
#765
b100 $
b100 *
b100100 (
#768
b0 ,
b0 -
b10 .
b100 2
1'
1+
#772
0'
0+
#775
b0 3
b1 6
#776
b10 7
b0 4
1'
1+
#778
b1000 &
#780
0'
0+
#784
b1000 0
b1000 !
1'
1+
b10 5
#786
b101 $
b101 *
b100101 (
#788
0'
0+
#792
b10 ,
b101 2
1'
1+
#796
0'
0+
#799
b1 3
#800
b10 4
1'
1+
#802
b1010 &
#804
0'
0+
#807
b110 $
b110 *
b100110 (
#808
b0 ,
b10 -
b1010 0
b1010 !
b110 2
1'
1+
#812
0'
0+
#815
b10 3
#816
b100 4
1'
1+
#818
b1100 &
#820
0'
0+
#824
b1100 0
b1100 !
1'
1+
b11 5
#828
0'
0+
b111 $
b111 *
b100111 (
#832
b10 ,
b111 2
1'
1+
#836
0'
0+
#839
b11 3
#840
b110 4
1'
1+
#842
b1110 &
#844
0'
0+
#848
b1110 0
b1110 !
1'
1+
#849
b1000 $
b1000 *
b101000 (
#852
0'
0+
#856
b0 ,
b0 -
b0 .
b10 /
b1000 2
1'
1+
#860
0'
0+
#863
b0 3
b10 6
#864
b100 7
b0 4
1'
1+
#866
b10000 &
#868
0'
0+
#870
b1001 $
b1001 *
b101001 (
#872
b10 ,
b10000 0
b10000 !
b1001 2
1'
1+
b100 5
#876
0'
0+
#879
b1 3
#880
b10 4
1'
1+
#882
b10010 &
#884
0'
0+
#888
b10010 0
b10010 !
1'
1+
#891
b1010 $
b1010 *
b101010 (
#892
0'
0+
#896
b0 ,
b10 -
b1010 2
1'
1+
#900
0'
0+
#903
b10 3
#904
b100 4
1'
1+
#906
b10100 &
#908
0'
0+
#912
b10 ,
b1011 2
b10100 0
b10100 !
1'
1+
b1011 $
b1011 *
b101 5
b101011 (
#916
0'
0+
#919
b11 3
#920
b110 4
1'
1+
#922
b10110 &
#924
0'
0+
#928
b10110 0
b10110 !
1'
1+
#932
0'
0+
#933
b1100 $
b1100 *
b101100 (
#936
b0 ,
b0 -
b10 .
b1100 2
1'
1+
#940
0'
0+
#943
b0 3
b11 6
#944
b110 7
b0 4
1'
1+
#946
b11000 &
#948
0'
0+
#952
b11000 0
b11000 !
1'
1+
b110 5
#954
b1101 $
b1101 *
b101101 (
#956
0'
0+
#960
b10 ,
b1101 2
1'
1+
#964
0'
0+
#967
b1 3
#968
b10 4
1'
1+
#970
b11010 &
#972
0'
0+
#975
b1110 $
b1110 *
b101110 (
#976
b0 ,
b10 -
b1110 2
b11010 0
b11010 !
1'
1+
#980
0'
0+
#983
b10 3
#984
b100 4
1'
1+
#986
b11100 &
#988
0'
0+
#992
b11100 0
b11100 !
1'
1+
b111 5
#996
0'
0+
b1111 $
b1111 *
b101111 (
#1000
b10 ,
b1111 2
1'
1+
#1004
0'
0+
#1007
b11 3
#1008
b110 4
1'
1+
#1010
b11110 &
#1012
0'
0+
#1016
b11110 0
b11110 !
1'
1+
#1017
b11 "
b11 )
b0 $
b0 *
b110000 (
#1020
0'
0+
#1024
b0 /
b0 .
b0 -
b0 ,
b0 2
b11 1
1'
1+
#1028
0'
0+
#1031
b0 6
b0 3
#1032
b0 7
b0 4
1'
1+
#1034
b0 &
#1036
0'
0+
#1038
b1 $
b1 *
b110001 (
#1040
b11 ,
b1 2
b0 0
b0 !
1'
1+
b0 5
#1044
0'
0+
#1047
b1 3
#1048
b11 4
1'
1+
#1050
b11 &
#1052
0'
0+
#1056
b11 0
b11 !
1'
1+
#1059
b10 $
b10 *
b110010 (
#1060
0'
0+
#1064
b0 ,
b11 -
b10 2
1'
1+
#1068
0'
0+
#1071
b11 3
#1072
b110 4
1'
1+
#1074
b110 &
#1076
0'
0+
#1080
b11 ,
b110 0
b110 !
b11 2
1'
1+
b11 $
b11 *
b1 5
b110011 (
#1084
0'
0+
#1087
b100 3
#1088
b1001 4
1'
1+
#1090
b1001 &
#1092
0'
0+
#1096
b1001 0
b1001 !
1'
1+
b10 5
#1100
0'
0+
#1101
b100 $
b100 *
b110100 (
#1104
b0 ,
b0 -
b11 .
b100 2
1'
1+
#1108
0'
0+
#1111
b0 3
b1 6
#1112
b11 7
b0 4
1'
1+
#1114
b1100 &
#1116
0'
0+
#1120
b1100 0
b1100 !
1'
1+
b11 5
#1122
b101 $
b101 *
b110101 (
#1124
0'
0+
#1128
b11 ,
b101 2
1'
1+
#1132
0'
0+
#1135
b1 3
#1136
b11 4
1'
1+
#1138
b1111 &
#1140
0'
0+
#1143
b110 $
b110 *
b110110 (
#1144
b0 ,
b11 -
b1111 0
b1111 !
b110 2
1'
1+
#1148
0'
0+
#1151
b11 3
#1152
b110 4
1'
1+
#1154
b10010 &
#1156
0'
0+
#1160
b10010 0
b10010 !
1'
1+
b100 5
#1164
0'
0+
b111 $
b111 *
b110111 (
#1168
b11 ,
b111 2
1'
1+
#1172
0'
0+
#1175
b100 3
#1176
b1001 4
1'
1+
#1178
b10101 &
#1180
0'
0+
#1184
b10101 0
b10101 !
1'
1+
b101 5
#1185
b1000 $
b1000 *
b111000 (
#1188
0'
0+
#1192
b0 ,
b0 -
b0 .
b11 /
b1000 2
1'
1+
#1196
0'
0+
#1199
b0 3
b11 6
#1200
b110 7
b0 4
1'
1+
#1202
b11000 &
#1204
0'
0+
#1206
b1001 $
b1001 *
b111001 (
#1208
b11 ,
b11000 0
b11000 !
b1001 2
1'
1+
b110 5
#1212
0'
0+
#1215
b1 3
#1216
b11 4
1'
1+
#1218
b11011 &
#1220
0'
0+
#1224
b11011 0
b11011 !
1'
1+
#1227
b1010 $
b1010 *
b111010 (
#1228
0'
0+
#1232
b0 ,
b11 -
b1010 2
1'
1+
#1236
0'
0+
#1239
b11 3
#1240
b110 4
1'
1+
#1242
b11110 &
#1244
0'
0+
#1248
b11 ,
b1011 2
b11110 0
b11110 !
1'
1+
b1011 $
b1011 *
b111 5
b111011 (
#1252
0'
0+
#1255
b100 3
#1256
b1001 4
1'
1+
#1258
b100001 &
#1260
0'
0+
#1264
b100001 0
b100001 !
1'
1+
b1000 5
#1268
0'
0+
#1269
b1100 $
b1100 *
b111100 (
#1272
b0 ,
b0 -
b11 .
b1100 2
1'
1+
#1276
0'
0+
#1279
b0 3
b100 6
#1280
b1001 7
b0 4
1'
1+
#1282
b100100 &
#1284
0'
0+
#1288
b100100 0
b100100 !
1'
1+
b1001 5
#1290
b1101 $
b1101 *
b111101 (
#1292
0'
0+
#1296
b11 ,
b1101 2
1'
1+
#1300
0'
0+
#1303
b1 3
#1304
b11 4
1'
1+
#1306
b100111 &
#1308
0'
0+
#1311
b1110 $
b1110 *
b111110 (
#1312
b0 ,
b11 -
b1110 2
b100111 0
b100111 !
1'
1+
#1316
0'
0+
#1319
b11 3
#1320
b110 4
1'
1+
#1322
b101010 &
#1324
0'
0+
#1328
b101010 0
b101010 !
1'
1+
b1010 5
#1332
0'
0+
b1111 $
b1111 *
b111111 (
#1336
b11 ,
b1111 2
1'
1+
#1340
0'
0+
#1343
b100 3
#1344
b1001 4
1'
1+
#1346
b101101 &
#1348
0'
0+
#1352
b101101 0
b101101 !
1'
1+
b1011 5
#1353
b100 "
b100 )
b0 $
b0 *
b1000000 (
#1356
0'
0+
#1360
b0 /
b0 .
b0 -
b0 ,
b0 2
b100 1
1'
1+
#1364
0'
0+
#1367
b0 6
b0 3
#1368
b0 7
b0 4
1'
1+
#1370
b0 &
#1372
0'
0+
#1374
b1 $
b1 *
b1000001 (
#1376
b100 ,
b1 2
b0 0
b0 !
1'
1+
b0 5
#1380
0'
0+
#1383
b10 3
#1384
b100 4
1'
1+
#1386
b100 &
#1388
0'
0+
#1392
b100 0
b100 !
1'
1+
b1 5
#1395
b10 $
b10 *
b1000010 (
#1396
0'
0+
#1400
b0 ,
b100 -
b10 2
1'
1+
#1404
0'
0+
#1407
b100 3
#1408
b1000 4
1'
1+
#1410
b1000 &
#1412
0'
0+
#1416
b100 ,
b1000 0
b1000 !
b11 2
1'
1+
b11 $
b11 *
b10 5
b1000011 (
#1420
0'
0+
#1423
b110 3
#1424
b1100 4
1'
1+
#1426
b1100 &
#1428
0'
0+
#1432
b1100 0
b1100 !
1'
1+
b11 5
#1436
0'
0+
#1437
b100 $
b100 *
b1000100 (
#1440
b0 ,
b0 -
b100 .
b100 2
1'
1+
#1444
0'
0+
#1447
b0 3
b10 6
#1448
b100 7
b0 4
1'
1+
#1450
b10000 &
#1452
0'
0+
#1456
b10000 0
b10000 !
1'
1+
b100 5
#1458
b101 $
b101 *
b1000101 (
#1460
0'
0+
#1464
b100 ,
b101 2
1'
1+
#1468
0'
0+
#1471
b10 3
#1472
b100 4
1'
1+
#1474
b10100 &
#1476
0'
0+
#1479
b110 $
b110 *
b1000110 (
#1480
b0 ,
b100 -
b10100 0
b10100 !
b110 2
1'
1+
b101 5
#1484
0'
0+
#1487
b100 3
#1488
b1000 4
1'
1+
#1490
b11000 &
#1492
0'
0+
#1496
b11000 0
b11000 !
1'
1+
b110 5
#1500
0'
0+
b111 $
b111 *
b1000111 (
#1504
b100 ,
b111 2
1'
1+
#1508
0'
0+
#1511
b110 3
#1512
b1100 4
1'
1+
#1514
b11100 &
#1516
0'
0+
#1520
b11100 0
b11100 !
1'
1+
b111 5
#1521
b1000 $
b1000 *
b1001000 (
#1524
0'
0+
#1528
b0 ,
b0 -
b0 .
b100 /
b1000 2
1'
1+
#1532
0'
0+
#1535
b0 3
b100 6
#1536
b1000 7
b0 4
1'
1+
#1538
b100000 &
#1540
0'
0+
#1542
b1001 $
b1001 *
b1001001 (
#1544
b100 ,
b100000 0
b100000 !
b1001 2
1'
1+
b1000 5
#1548
0'
0+
#1551
b10 3
#1552
b100 4
1'
1+
#1554
b100100 &
#1556
0'
0+
#1560
b100100 0
b100100 !
1'
1+
b1001 5
#1563
b1010 $
b1010 *
b1001010 (
#1564
0'
0+
#1568
b0 ,
b100 -
b1010 2
1'
1+
#1572
0'
0+
#1575
b100 3
#1576
b1000 4
1'
1+
#1578
b101000 &
#1580
0'
0+
#1584
b100 ,
b1011 2
b101000 0
b101000 !
1'
1+
b1011 $
b1011 *
b1010 5
b1001011 (
#1588
0'
0+
#1591
b110 3
#1592
b1100 4
1'
1+
#1594
b101100 &
#1596
0'
0+
#1600
b101100 0
b101100 !
1'
1+
b1011 5
#1604
0'
0+
#1605
b1100 $
b1100 *
b1001100 (
#1608
b0 ,
b0 -
b100 .
b1100 2
1'
1+
#1612
0'
0+
#1615
b0 3
b110 6
#1616
b1100 7
b0 4
1'
1+
#1618
b110000 &
#1620
0'
0+
#1624
b110000 0
b110000 !
1'
1+
b1100 5
#1626
b1101 $
b1101 *
b1001101 (
#1628
0'
0+
#1632
b100 ,
b1101 2
1'
1+
#1636
0'
0+
#1639
b10 3
#1640
b100 4
1'
1+
#1642
b110100 &
#1644
0'
0+
#1647
b1110 $
b1110 *
b1001110 (
#1648
b0 ,
b100 -
b1110 2
b110100 0
b110100 !
1'
1+
b1101 5
#1652
0'
0+
#1655
b100 3
#1656
b1000 4
1'
1+
#1658
b111000 &
#1660
0'
0+
#1664
b111000 0
b111000 !
1'
1+
b1110 5
#1668
0'
0+
b1111 $
b1111 *
b1001111 (
#1672
b100 ,
b1111 2
1'
1+
#1676
0'
0+
#1679
b110 3
#1680
b1100 4
1'
1+
#1682
b111100 &
#1684
0'
0+
#1688
b111100 0
b111100 !
1'
1+
b1111 5
#1689
b101 "
b101 )
b0 $
b0 *
b1010000 (
#1692
0'
0+
#1696
b0 /
b0 .
b0 -
b0 ,
b0 2
b101 1
1'
1+
#1700
0'
0+
#1703
b0 6
b0 3
#1704
b0 7
b0 4
1'
1+
#1706
b0 &
#1708
0'
0+
#1710
b1 $
b1 *
b1010001 (
#1712
b101 ,
b1 2
b0 0
b0 !
1'
1+
b0 5
#1716
0'
0+
#1719
b10 3
#1720
b101 4
1'
1+
#1722
b101 &
#1724
0'
0+
#1728
b101 0
b101 !
1'
1+
b1 5
#1731
b10 $
b10 *
b1010010 (
#1732
0'
0+
#1736
b0 ,
b101 -
b10 2
1'
1+
#1740
0'
0+
#1743
b101 3
#1744
b1010 4
1'
1+
#1746
b1010 &
#1748
0'
0+
#1752
b101 ,
b1010 0
b1010 !
b11 2
1'
1+
b11 $
b11 *
b10 5
b1010011 (
#1756
0'
0+
#1759
b111 3
#1760
b1111 4
1'
1+
#1762
b1111 &
#1764
0'
0+
#1768
b1111 0
b1111 !
1'
1+
b11 5
#1772
0'
0+
#1773
b100 $
b100 *
b1010100 (
#1776
b0 ,
b0 -
b101 .
b100 2
1'
1+
#1780
0'
0+
#1783
b0 3
b10 6
#1784
b101 7
b0 4
1'
1+
#1786
b10100 &
#1788
0'
0+
#1792
b10100 0
b10100 !
1'
1+
b101 5
#1794
b101 $
b101 *
b1010101 (
#1796
0'
0+
#1800
b101 ,
b101 2
1'
1+
#1804
0'
0+
#1807
b10 3
#1808
b101 4
1'
1+
#1810
b11001 &
#1812
0'
0+
#1815
b110 $
b110 *
b1010110 (
#1816
b0 ,
b101 -
b11001 0
b11001 !
b110 2
1'
1+
b110 5
#1820
0'
0+
#1823
b101 3
#1824
b1010 4
1'
1+
#1826
b11110 &
#1828
0'
0+
#1832
b11110 0
b11110 !
1'
1+
b111 5
#1836
0'
0+
b111 $
b111 *
b1010111 (
#1840
b101 ,
b111 2
1'
1+
#1844
0'
0+
#1847
b111 3
#1848
b1111 4
1'
1+
#1850
b100011 &
#1852
0'
0+
#1856
b100011 0
b100011 !
1'
1+
b1000 5
#1857
b1000 $
b1000 *
b1011000 (
#1860
0'
0+
#1864
b0 ,
b0 -
b0 .
b101 /
b1000 2
1'
1+
#1868
0'
0+
#1871
b0 3
b101 6
#1872
b1010 7
b0 4
1'
1+
#1874
b101000 &
#1876
0'
0+
#1878
b1001 $
b1001 *
b1011001 (
#1880
b101 ,
b101000 0
b101000 !
b1001 2
1'
1+
b1010 5
#1884
0'
0+
#1887
b10 3
#1888
b101 4
1'
1+
#1890
b101101 &
#1892
0'
0+
#1896
b101101 0
b101101 !
1'
1+
b1011 5
#1899
b1010 $
b1010 *
b1011010 (
#1900
0'
0+
#1904
b0 ,
b101 -
b1010 2
1'
1+
#1908
0'
0+
#1911
b101 3
#1912
b1010 4
1'
1+
#1914
b110010 &
#1916
0'
0+
#1920
b101 ,
b1011 2
b110010 0
b110010 !
1'
1+
b1011 $
b1011 *
b1100 5
b1011011 (
#1924
0'
0+
#1927
b111 3
#1928
b1111 4
1'
1+
#1930
b110111 &
#1932
0'
0+
#1936
b110111 0
b110111 !
1'
1+
b1101 5
#1940
0'
0+
#1941
b1100 $
b1100 *
b1011100 (
#1944
b0 ,
b0 -
b101 .
b1100 2
1'
1+
#1948
0'
0+
#1951
b0 3
b111 6
#1952
b1111 7
b0 4
1'
1+
#1954
b111100 &
#1956
0'
0+
#1960
b111100 0
b111100 !
1'
1+
b1111 5
#1962
b1101 $
b1101 *
b1011101 (
#1964
0'
0+
#1968
b101 ,
b1101 2
1'
1+
#1972
0'
0+
#1975
b10 3
#1976
b101 4
1'
1+
#1978
b1000001 &
#1980
0'
0+
#1983
b1110 $
b1110 *
b1011110 (
#1984
b0 ,
b101 -
b1110 2
b1000001 0
b1000001 !
1'
1+
b10000 5
#1988
0'
0+
#1991
b101 3
#1992
b1010 4
1'
1+
#1994
b1000110 &
#1996
0'
0+
#2000
b1000110 0
b1000110 !
1'
1+
b10001 5
#2004
0'
0+
b1111 $
b1111 *
b1011111 (
#2008
b101 ,
b1111 2
1'
1+
#2012
0'
0+
#2015
b111 3
#2016
b1111 4
1'
1+
#2018
b1001011 &
#2020
0'
0+
#2024
b1001011 0
b1001011 !
1'
1+
b10010 5
#2025
b110 "
b110 )
b0 $
b0 *
b1100000 (
#2028
0'
0+
#2032
b0 /
b0 .
b0 -
b0 ,
b0 2
b110 1
1'
1+
#2036
0'
0+
#2039
b0 6
b0 3
#2040
b0 7
b0 4
1'
1+
#2042
b0 &
#2044
0'
0+
#2046
b1 $
b1 *
b1100001 (
#2048
b110 ,
b1 2
b0 0
b0 !
1'
1+
b0 5
#2052
0'
0+
#2055
b11 3
#2056
b110 4
1'
1+
#2058
b110 &
#2060
0'
0+
#2064
b110 0
b110 !
1'
1+
b1 5
#2067
b10 $
b10 *
b1100010 (
#2068
0'
0+
#2072
b0 ,
b110 -
b10 2
1'
1+
#2076
0'
0+
#2079
b110 3
#2080
b1100 4
1'
1+
#2082
b1100 &
#2084
0'
0+
#2088
b110 ,
b1100 0
b1100 !
b11 2
1'
1+
b11 $
b11 *
b11 5
b1100011 (
#2092
0'
0+
#2095
b1001 3
#2096
b10010 4
1'
1+
#2098
b10010 &
#2100
0'
0+
#2104
b10010 0
b10010 !
1'
1+
b100 5
#2108
0'
0+
#2109
b100 $
b100 *
b1100100 (
#2112
b0 ,
b0 -
b110 .
b100 2
1'
1+
#2116
0'
0+
#2119
b0 3
b11 6
#2120
b110 7
b0 4
1'
1+
#2122
b11000 &
#2124
0'
0+
#2128
b11000 0
b11000 !
1'
1+
b110 5
#2130
b101 $
b101 *
b1100101 (
#2132
0'
0+
#2136
b110 ,
b101 2
1'
1+
#2140
0'
0+
#2143
b11 3
#2144
b110 4
1'
1+
#2146
b11110 &
#2148
0'
0+
#2151
b110 $
b110 *
b1100110 (
#2152
b0 ,
b110 -
b11110 0
b11110 !
b110 2
1'
1+
b111 5
#2156
0'
0+
#2159
b110 3
#2160
b1100 4
1'
1+
#2162
b100100 &
#2164
0'
0+
#2168
b100100 0
b100100 !
1'
1+
b1001 5
#2172
0'
0+
b111 $
b111 *
b1100111 (
#2176
b110 ,
b111 2
1'
1+
#2180
0'
0+
#2183
b1001 3
#2184
b10010 4
1'
1+
#2186
b101010 &
#2188
0'
0+
#2192
b101010 0
b101010 !
1'
1+
b1010 5
#2193
b1000 $
b1000 *
b1101000 (
#2196
0'
0+
#2200
b0 ,
b0 -
b0 .
b110 /
b1000 2
1'
1+
#2204
0'
0+
#2207
b0 3
b110 6
#2208
b1100 7
b0 4
1'
1+
#2210
b110000 &
#2212
0'
0+
#2214
b1001 $
b1001 *
b1101001 (
#2216
b110 ,
b110000 0
b110000 !
b1001 2
1'
1+
b1100 5
#2220
0'
0+
#2223
b11 3
#2224
b110 4
1'
1+
#2226
b110110 &
#2228
0'
0+
#2232
b110110 0
b110110 !
1'
1+
b1101 5
#2235
b1010 $
b1010 *
b1101010 (
#2236
0'
0+
#2240
b0 ,
b110 -
b1010 2
1'
1+
#2244
0'
0+
#2247
b110 3
#2248
b1100 4
1'
1+
#2250
b111100 &
#2252
0'
0+
#2256
b110 ,
b1011 2
b111100 0
b111100 !
1'
1+
b1011 $
b1011 *
b1111 5
b1101011 (
#2260
0'
0+
#2263
b1001 3
#2264
b10010 4
1'
1+
#2266
b1000010 &
#2268
0'
0+
#2272
b1000010 0
b1000010 !
1'
1+
b10000 5
#2276
0'
0+
#2277
b1100 $
b1100 *
b1101100 (
#2280
b0 ,
b0 -
b110 .
b1100 2
1'
1+
#2284
0'
0+
#2287
b0 3
b1001 6
#2288
b10010 7
b0 4
1'
1+
#2290
b1001000 &
#2292
0'
0+
